{
  "meta": {
    "election_id": "ol-kalou-2026",
    "generated_at": "2026-07-16T06:52:55.422358+00:00",
    "collection_cursor": "2026-07-16T06:52:55.422358+00:00",
    "mode": "demo",
    "disclaimer": "This dashboard measures online discussion, not voter intention. X users and news coverage are not representative of Ol Kalou voters. Sentiment models can misread sarcasm, Kikuyu, Kiswahili, Sheng, names, quotations, and political slogans. Official election information and results come from IEBC.",
    "alert_disclaimer": "Alerts reflect volume and repetition in public conversation, not confirmed events. Only entries marked 'officially confirmed' have been verified by an authority."
  },
  "summary": {
    "total_relevant_items": 20,
    "x_items": 15,
    "news_items": 3,
    "unique_source_estimate": 17,
    "duplicated_share": 0.0,
    "overall_balance": {
      "positive": 6,
      "neutral": 2,
      "negative": 9,
      "unscored": 3
    }
  },
  "timeline": [],
  "candidates": [
    {
      "id": "nyagah_samuel",
      "name": "Samuel Muchina Nyagah",
      "party": "UDA",
      "suppressed": false,
      "mention_count": 6,
      "positive": 3,
      "neutral": 1,
      "negative": 1,
      "unscored": 1,
      "net_sentiment_index": 40.0,
      "source_mix": {
        "x": 4,
        "news": 1,
        "manual": 1
      },
      "confidence": "higher"
    },
    {
      "id": "ngotho_sammy",
      "name": "Sammy Kamau Ngotho",
      "party": "DCP",
      "suppressed": true,
      "reason": "Fewer than 5 independent items this window."
    },
    {
      "id": "kigwa_wilson",
      "name": "Wilson Kigwa",
      "party": "Jubilee Party",
      "suppressed": true,
      "reason": "Fewer than 5 independent items this window."
    },
    {
      "id": "kamau_timothy",
      "name": "Timothy Kamau",
      "party": "People's Renaissance Movement",
      "suppressed": true,
      "reason": "Fewer than 5 independent items this window."
    },
    {
      "id": "muchiri_edwin",
      "name": "Edwin Muchiri",
      "party": "PNU",
      "suppressed": true,
      "reason": "Fewer than 5 independent items this window."
    },
    {
      "id": "waithaka_stephen",
      "name": "Stephen Wanyoike Waithaka",
      "party": "National Liberal Party",
      "suppressed": true,
      "reason": "Fewer than 5 independent items this window."
    },
    {
      "id": "njoroge_rachael",
      "name": "Rachael Wangui Njoroge",
      "party": "People's Democratic Party",
      "suppressed": true,
      "reason": "Fewer than 5 independent items this window."
    },
    {
      "id": "mathenge_edward",
      "name": "Edward Mathenge / Edward Mwaniki",
      "party": "Kenya Moja Movement",
      "suppressed": true,
      "reason": "Fewer than 5 independent items this window."
    },
    {
      "id": "abdullahi_abdifatah",
      "name": "Abdifatah Hussein Abdullahi",
      "party": "Federal Party of Kenya",
      "suppressed": true,
      "reason": "Fewer than 5 independent items this window."
    }
  ],
  "topics": [
    {
      "topic": "admin",
      "suppressed": true
    },
    {
      "topic": "security",
      "suppressed": false,
      "item_count": 10,
      "positive": 2,
      "negative": 7,
      "confidence": "higher"
    },
    {
      "topic": "integrity",
      "suppressed": true
    },
    {
      "topic": "misinformation",
      "suppressed": true
    },
    {
      "topic": "accessibility",
      "suppressed": true
    },
    {
      "topic": "results",
      "suppressed": true
    },
    {
      "topic": "logistics",
      "suppressed": true
    },
    {
      "topic": "local_economy",
      "suppressed": true
    },
    {
      "topic": "weather",
      "suppressed": true
    }
  ],
  "sources": [
    {
      "outlet": "example-news.co.ke",
      "count": 3
    }
  ],
  "articles": [
    {
      "headline": "Nyagah closes campaign in Ol Kalou",
      "outlet": "example-news.co.ke",
      "timestamp": "2026-07-16T06:52:55.416548+00:00",
      "url": null,
      "sentiment_label": "positive"
    },
    {
      "headline": "IEBC reports smooth opening",
      "outlet": "example-news.co.ke",
      "timestamp": "2026-07-16T06:52:55.416548+00:00",
      "url": null,
      "sentiment_label": "unscored"
    },
    {
      "headline": "Security deployed after clash reported",
      "outlet": "example-news.co.ke",
      "timestamp": "2026-07-16T06:52:55.416548+00:00",
      "url": null,
      "sentiment_label": "positive"
    }
  ],
  "quality": {
    "exact_and_near_duplicate_rate": 0.0,
    "repost_share": 0.0,
    "source_concentration": 0.15,
    "unsupported_language_share": 0.15,
    "anomaly_flags": [],
    "sampling_warnings": []
  },
  "alerts": [
    {
      "id": "ol-kalou-2026:security",
      "category": "security",
      "status": "reported",
      "first_seen": "2026-07-16T06:46:00.765452+00:00",
      "last_updated": "2026-07-16T06:52:55.416548+00:00",
      "item_count": 10,
      "independent_source_count": 9,
      "confidence": "higher",
      "summary": "10 independent items across 9 sources mention security-related terms in the current window.",
      "override_applied": false
    }
  ]
}