{
  "schema": "kenya.election.ocr-summary.v1",
  "pipeline_version": "2026.07.14-layout-v2",
  "election_id": "malava-2025",
  "generated_at": "2026-07-15T01:18:09.913233Z",
  "engine_mode": "embedded",
  "engines_available": [],
  "documents_total": 198,
  "pages_total": 198,
  "pages_processed": 198,
  "layout_assisted_pages": 185,
  "form35a_detected": 191,
  "form35b_detected": 0,
  "streams_matched": 184,
  "review_rows": 177,
  "routes": {
    "QUARANTINE": 189,
    "UNCLASSIFIED": 7,
    "OCR_BENCHMARK_REVIEW": 2
  },
  "errors": [],
  "hierarchy": {
    "changed": true,
    "mapped": 162,
    "unresolved": 36,
    "errors": []
  },
  "review_queue": "data/elections/malava-2025/ocr/review_queue.csv",
  "inventory": "data/elections/malava-2025/ocr/document_inventory.json",
  "auto_publication": false,
  "note": "OCR output is a pre-fill only. Handwritten cells are read with layout anchors and arithmetic reconciliation, but no historical stream is added to the public tally until human review and statutory validation are complete."
}
