{
  "schema": "kenya.election.ocr-extraction.v1",
  "pipeline_version": "2026.07.14-layout-v2",
  "election_id": "banissa-2025",
  "page_id": "8e3af80565e0afcd-p001",
  "source_path": "data/public/elections/banissa-2025/forms/009040019600305/v1_8e3af80565e0.pdf",
  "source_sha256": "8e3af80565e0afcd792d10f9d04f1d409b7690871a72f345e30bc767d643a5c1",
  "source_filename": "v1_8e3af80565e0.pdf",
  "public_url": "../data/public/elections/banissa-2025/forms/uploaded/8e3af80565e0afcd.pdf#page=1",
  "page_no": 1,
  "form_type": "35A",
  "stream_key": "040-0196-003-05",
  "match_method": "STATION_NAME_AND_STREAM",
  "engine": "tesseract",
  "confidence": 0.26,
  "text_length": 2411,
  "text_preview": "-_—— enn rn re er rer c eee ern eer n ccc ccc cn cnccccc ce cceeccccccnnnnn nee TS ee NEESCSesnareee\n- FORM35A = YD = GD Se . ee = z ; 7 1EBC 2 100 Reg. 75 2) Pe\n: MEMBER OF THE NATIONAL ASSEMBLY BY-ELECTION RESULTS\nAT THE POLLING STATION\nName of Polling Station BANISA PRIMARY SCHOOL POLLING STATION 5 of 5 Code __909040019600305\nWard BANISSA Code _ 0196 0\nConstituency BANISSA pe cL SMOORAL ayn /NOEPENT\nCounty MANDERA Code __ 009\nNumber of votes cast in favour of each candidate:\n| Name of Candidate No. of Valid Votes Obtained\n[\"1. HASSAN AHMED MAALIM —— ee\n2. MOHAMED NURDIN MAALIM\nTotal number of valid votes cast JSPR Sc OR REROR ST PROEN Tee ORO RROSCON DL Gy\nPolling Station Counts Decision{s} on disputed votes if any\n[1] Toto Number of Raistere Vater nthe Paling Staton,\nToll Number Rejected Balt Papers esc conter ion auaunorseaBenlomPReee ON OB SUNG HOE\nTotal Number of Rejection Objected to Ballot Papers; PPR. 0C CONN NOB OLN NDENTELEC TD anon CoM NDARIESCRLEG\n[4 | Tota Number oF spied oles asso ono amrse Lec ronn MpoeUo ON TCR OuaESSe A\nTt Nurber fai Votes Cast BSc Ner cus oka aon oAT ECONO EC URE\nDeclaration\nWe, the undersigned, being present when the results of the count were announced, do hereby declare that the results shown above are true\nand accurate count of the ballots in AISA PRIMAL Petting Stadion ANISST Constituency.\nPresiding Otticer: MO PAM EdVveDR SFIO4¢a wear prt pate ZI- UA 25\n2 2 : ‘> -\nDeputy Presiding Officer: JARIRA MAKI SS i+ ope palG tt Date 27 [1 {20\nCER\nAgents or Candidates (if present) ea\n[e| _nemseasoesroe [moa] Fay ineteerenasoe [oom | Snare | Om |\n21 SSEIN JOR S639qHe | Vpp pfayseeees AMM adios\na MSS tANDB OU TENSION gu MiSSION Temps ARIES Sr nya pF ENO HTELEC je OMMISS ONQNON CoO PTELEC TONY\nSGSBOPCENTELECT Osea SIONINDEPEN Cal > RAL ANPBOUW- ENOENTELEC ONO BSCR IND ARIESC Oss CLORALANDEN DES WARE WMI\nRage ORAL ANDBOL CE PEND SATE. EGON SN Ces QUNDARIESCUELECTORALAND NO” GN Nove COMMS ON 114 HOBOUNDART TORNOON EC ONIN\nen con merc Mae oe eg ee ee es eee\nFa KEL RIONINO BE OUN paste sCOMN ANNO CO NN AYO NDEN Ey «SC OmmtnclONINOSaPOLE OSUHON ECTORA! oS/PKINor PENDENT OWN ag\nSUTRA SrUDEN TA Scr ean cal ON PON Cc ONINON, f cro MSS OMAN DE NDE uN NCCNOL OMEN R O ULE AEN UNA ECTORNOe Rp LCRA\nReasons for Refusal to Sign {if any}\nPresiding Officer's Comments: ? LN re aes i Be LO\nTite ELection Otic / Mitte\nWH GR ores meee, IPINAOIERANCE Pan (ME Arem",
  "parsed": {
    "fields": {
      "candidate_UDA": {
        "value": 1,
        "confidence": 0.78
      },
      "candidate_UPA": {
        "value": 2,
        "confidence": 0.78
      },
      "registered": {
        "value": null,
        "confidence": 0.0
      },
      "rejected": {
        "value": null,
        "confidence": 0.0
      },
      "total_valid": {
        "value": null,
        "confidence": 0.0
      },
      "total_cast": {
        "value": null,
        "confidence": 0.0
      },
      "rejection_objections": {
        "value": null,
        "confidence": 0.0
      },
      "disputed_votes": {
        "value": null,
        "confidence": 0.0
      }
    },
    "evidence": {
      "candidate_UDA": "[\"1. HASSAN AHMED MAALIM —— ee",
      "candidate_UPA": "2. MOHAMED NURDIN MAALIM",
      "registered": null,
      "rejected": null,
      "total_valid": null,
      "total_cast": null,
      "rejection_objections": null,
      "disputed_votes": null
    }
  },
  "checks": {
    "V01": "NOT_RUN",
    "V02": "NOT_RUN",
    "V03": "NOT_RUN",
    "V07": "NOT_RUN"
  },
  "route": "QUARANTINE",
  "auto_published": false,
  "extracted_at": "2026-07-14T17:21:14.653938Z"
}
